thaillm/__init__.py
thaillm/tokenize/Tokenize.py
thaillm/tokenize/__init__.py
thaillm/tokenize/input/th_tokenizer_32000.model
thaillm-0.1.2.dist-info/LICENSE.txt
thaillm-0.1.2.dist-info/METADATA
thaillm-0.1.2.dist-info/WHEEL
thaillm-0.1.2.dist-info/top_level.txt
thaillm-0.1.2.dist-info/RECORD
