Metadata-Version: 2.1
Name: thaillm
Version: 0.1.2
Summary: Thai large language model(LLM)
Home-page: 
Author: bablueza
Author-email: bablueza@gmail.com
License: MIT
Platform: UNKNOWN
Requires-Python: >=3.8
License-File: LICENSE.txt
Requires-Dist: transformers
Requires-Dist: sentencepiece
